{
  "version": "7",
  "dialect": "postgresql",
  "entries": [
    {
      "idx": 0,
      "version": "7",
      "when": 1782502902859,
      "tag": "0000_init",
      "breakpoints": true
    },
    {
      "idx": 1,
      "version": "7",
      "when": 1782504912470,
      "tag": "0001_add_discovery_candidates",
      "breakpoints": true
    },
    {
      "idx": 2,
      "version": "7",
      "when": 1783713636426,
      "tag": "0002_add_ig_handle_to_creators",
      "breakpoints": true
    },
    {
      "idx": 3,
      "version": "7",
      "when": 1783718600735,
      "tag": "0003_cold_the_leader",
      "breakpoints": true
    },
    {
      "idx": 4,
      "version": "7",
      "when": 1783726408579,
      "tag": "0004_form-arrivals-to-your-call",
      "breakpoints": true
    }
  ]
}